payload_generator/__init__.py
payload_generator/__main__.py
payload_generator/brand_values.json
payload_generator/centene_sentences.txt
payload_generator/humana_sentences.txt
payload_generator/sentences.txt
payload_generator-0.6.1.dist-info/METADATA
payload_generator-0.6.1.dist-info/WHEEL
payload_generator-0.6.1.dist-info/entry_points.txt
payload_generator-0.6.1.dist-info/top_level.txt
payload_generator-0.6.1.dist-info/RECORD
