Metadata-Version: 2.2
Name: payload-generator
Version: 0.6.1
Summary: A package for generating payloads for sending to the Ingestion Gateway.
Home-page: https://gitlab-app.eng.qops.net/zkhatri/payload-generator
Author: Zeshan Khatri
Author-email: zkhatri@qualtrics.com
Classifier: Programming Language :: Python :: 2
Classifier: Programming Language :: Python :: 2.7
Classifier: Programming Language :: Python :: 3
Classifier: Programming Language :: Python :: 3.4
Classifier: Programming Language :: Python :: 3.5
Classifier: Programming Language :: Python :: 3.6
Classifier: Programming Language :: Python :: 3.7
Classifier: Programming Language :: Python :: 3.8
Classifier: Programming Language :: Python :: 3.9
Classifier: Programming Language :: Python :: 3.10
Classifier: Programming Language :: Python :: 3.11
Classifier: Programming Language :: Python :: 3.12
Requires-Dist: faker>=3.0.1
Requires-Dist: importlib-resources>=6.5.2
Dynamic: author
Dynamic: author-email
Dynamic: classifier
Dynamic: home-page
Dynamic: requires-dist
Dynamic: summary
